linecook/__init__.py
linecook/cli.py
linecook/config/__init__.py
linecook/config/core.py
linecook/config/parsers.py
linecook/config/tests/__init__.py
linecook/config/tests/test_parsers.py
linecook/parsers.py
linecook/patterns.py
linecook/recipes/__init__.py
linecook/recipes/dpkg_log.py
linecook/recipes/python.py
linecook/tests/__init__.py
linecook/tests/test_cli.py
linecook/tests/test_parsers.py
linecook/tests/test_patterns.py
linecook/transforms/__init__.py
linecook/transforms/core.py
linecook/transforms/logging.py
linecook/transforms/parse.py
linecook/transforms/tests/__init__.py
linecook/transforms/tests/test_core.py
linecook/transforms/tests/test_parse.py
linecook-0.4.0.dist-info/entry_points.txt
linecook-0.4.0.dist-info/LICENSE
linecook-0.4.0.dist-info/WHEEL
linecook-0.4.0.dist-info/METADATA
linecook-0.4.0.dist-info/RECORD
