Metadata-Version: 2.1
Name: linecook
Version: 0.4.0
Summary: Prepare lines of text for easy consumption
Home-page: https://github.com/tonysyu/linecook
License: BSD-3-Clause
Keywords: console,terminal,logging,parsing,color
Author: Tony S. Yu
Author-email: tsyu80@gmail.com
Classifier: Development Status :: 3 - Alpha
Classifier: Environment :: Console
Classifier: Intended Audience :: Developers
Classifier: License :: OSI Approved :: BSD License
Classifier: Programming Language :: Python :: 2
Classifier: Programming Language :: Python :: 2.7
Classifier: Programming Language :: Python :: 3
Classifier: Programming Language :: Python :: 3.4
Classifier: Programming Language :: Python :: 3.5
Classifier: Programming Language :: Python :: 3.6
Classifier: Programming Language :: Python :: 3.7
Classifier: Topic :: Software Development
Requires-Dist: future (>=0.15,<0.16)
Requires-Dist: termcolor (>=1.0.0,<2.0.0)
Requires-Dist: toolz (>=0.9.0,<0.10.0)
Project-URL: Documentation, https://linecook.readthedocs.io/
Project-URL: Repository, https://github.com/tonysyu/linecook
